jaxcmr/cmr.py
jaxcmr/context.py
jaxcmr/fitting.py
jaxcmr/helpers.py
jaxcmr/likelihood.py
jaxcmr/memory.py
jaxcmr/simulation.py
jaxcmr/summarize.py
jaxcmr/typing.py
jaxcmr-0.1.1.dist-info/METADATA
jaxcmr-0.1.1.dist-info/WHEEL
jaxcmr-0.1.1.dist-info/RECORD
